build/lib/build/lib/build/lib/build/lib/build/lib/chrono/__init__.py
build/lib/build/lib/build/lib/build/lib/chrono/__init__.py
build/lib/build/lib/build/lib/build/lib/streamlit_chrono/__init__.py
build/lib/build/lib/build/lib/chrono/__init__.py
build/lib/build/lib/build/lib/streamlit_chrono/__init__.py
build/lib/build/lib/chrono/__init__.py
build/lib/build/lib/streamlit_chrono/__init__.py
build/lib/chrono/__init__.py
build/lib/streamlit_chrono/__init__.py
chrono/__init__.py
chrono/frontend/build/asset-manifest.json
chrono/frontend/build/bootstrap.min.css
chrono/frontend/build/index.html
chrono/frontend/build/static/js/main.7714f0cc.js
chrono/frontend/build/static/js/main.7714f0cc.js.LICENSE.txt
chrono/frontend/build/static/js/main.7714f0cc.js.map
streamlit_chrono/__init__.py
streamlit_chrono/frontend/build/asset-manifest.json
streamlit_chrono/frontend/build/bootstrap.min.css
streamlit_chrono/frontend/build/index.html
streamlit_chrono/frontend/build/static/js/main.7714f0cc.js
streamlit_chrono/frontend/build/static/js/main.7714f0cc.js.LICENSE.txt
streamlit_chrono/frontend/build/static/js/main.7714f0cc.js.map
streamlit_chrono-0.0.2.dist-info/LICENSE
streamlit_chrono-0.0.2.dist-info/METADATA
streamlit_chrono-0.0.2.dist-info/WHEEL
streamlit_chrono-0.0.2.dist-info/top_level.txt
streamlit_chrono-0.0.2.dist-info/RECORD
