Metadata-Version: 2.1
Name: streamlit-chrono
Version: 0.0.2
Summary: Streamlit component that allows you to add Chrono Timeline
Home-page: https://github.com/keshavd/streamlit-chrono
Author: Keshav Dial
Author-email: keshav.dial@sanofi.com
Requires-Python: >=3.7
License-File: LICENSE
Requires-Dist: streamlit (>=0.63)
